MANIFEST.in
README.rst
setup.py
roach/__init__.py
roach/bits.py
roach/disasm.py
roach/main.py
roach/pe.py
roach/procmem.py
roach/short.py
roach/structure.py
roach/verify.py
roach.egg-info/PKG-INFO
roach.egg-info/SOURCES.txt
roach.egg-info/dependency_links.txt
roach.egg-info/entry_points.txt
roach.egg-info/requires.txt
roach.egg-info/top_level.txt
roach/compression/__init__.py
roach/compression/aplib.py
roach/compression/gzip.py
roach/crypto/__init__.py
roach/crypto/aes.py
roach/crypto/blowfish.py
roach/crypto/des3.py
roach/crypto/rc.py
roach/crypto/rsa.py
roach/crypto/xor.py
roach/hash/__init__.py
roach/hash/sha.py
roach/native/__init__.py
roach/native/aplib.py
roach/native/common.py
roach/native/components/aplib-32.dll
roach/native/components/aplib-32.so
roach/native/components/aplib-64.dll
roach/native/components/aplib-64.so
roach/string/__init__.py
roach/string/bin.py
roach/string/inet.py
roach/string/ops.py