Metadata-Version: 1.0
Name: roach
Version: 0.1
Summary: Cockroach is your primitive & immortal swiss army knife
Home-page: https://github.com/jbremer/roach
Author: Jurriaan Bremer
Author-email: jbr@cuckoo.sh
License: GPLv3
Platform: UNKNOWN
